terraformat/__init__.py
terraformat/address.py
terraformat/main.py
terraformat-0.1.8.dist-info/licenses/LICENSE
terraformat-0.1.8.dist-info/METADATA
terraformat-0.1.8.dist-info/WHEEL
terraformat-0.1.8.dist-info/entry_points.txt
terraformat-0.1.8.dist-info/top_level.txt
terraformat-0.1.8.dist-info/RECORD
