Metadata-Version: 2.4
Name: terraformat
Version: 0.1.8
Summary: A wrapper for the Terraform CLI that provides a formatted plan summary.
Home-page: https://github.com/henryupton/terraformat
Author: Henry Upton-Birdsall
Author-email: henryupton@gmail.com
Classifier: Programming Language :: Python :: 3
Classifier: License :: OSI Approved :: MIT License
Classifier: Operating System :: OS Independent
Classifier: Topic :: Software Development :: Build Tools
Requires-Python: >=3.7
License-File: LICENSE
Requires-Dist: click
Requires-Dist: tabulate
Provides-Extra: test
Requires-Dist: pytest; extra == "test"
Dynamic: author
Dynamic: author-email
Dynamic: classifier
Dynamic: description
Dynamic: description-content-type
Dynamic: home-page
Dynamic: license-file
Dynamic: provides-extra
Dynamic: requires-dist
Dynamic: requires-python
Dynamic: summary
